{
  "title": "Oracle Fusion Financials Training",
  "description": "Oracle fusion financials training covers concepts from the Basic level to the advanced level.  Whether you are an individual or corporate client we can customize training course content as per your requirement.  And can arrange this Oracle fusion financials training as per your pace.\n\nThis Oracle Fusion Financials training provides a comprehensive financial management solution, with extensive support for global companies across multiple industries.\n\nOracle Fusion Financials training will provide an in-depth understanding of your applications, including Accounting Hub, General Ledger, Payables, Receivables and Revenue Management and teach you how to setup, administer and use your Financials Cloud applications.",
  "curriculum": [],
  "url": "https://www.maxmunus.com/page/Oracle-Fusion-Financials-Training",
  "category": "Oracle Courses"
}